Pyfitting-0.9.1.dist-info/DESCRIPTION.rst
Pyfitting-0.9.1.dist-info/METADATA
Pyfitting-0.9.1.dist-info/RECORD
Pyfitting-0.9.1.dist-info/WHEEL
Pyfitting-0.9.1.dist-info/metadata.json
Pyfitting-0.9.1.dist-info/top_level.txt
pyfitting/__init__.py
pyfitting/fit.py
pyfitting/gui.py
pyfitting/modules/__init__.py
