Metadata-Version: 2.0
Name: Pyfitting
Version: 0.9.1
Summary: UNKNOWN
Home-page: https://github.com/jeppe742/pyfitting
Author: Jeppe Johan Waarkjaer Olsen
Author-email: UNKNOWN
License: UNKNOWN
Platform: UNKNOWN
Requires-Dist: autodiff
Requires-Dist: numpy
Requires-Dist: matplotlib
